uniswap/__init__.py
uniswap/cli.py
uniswap/constants.py
uniswap/decorators.py
uniswap/exceptions.py
uniswap/token.py
uniswap/tokens.py
uniswap/types.py
uniswap/uniswap.py
uniswap/util.py
uniswap/assets/erc20.abi
uniswap/assets/erc20b32.abi
uniswap/assets/uniswap-v1/exchange.abi
uniswap/assets/uniswap-v1/factory.abi
uniswap/assets/uniswap-v2/factory.abi
uniswap/assets/uniswap-v2/router02.abi
uniswap/assets/uniswap-v3/factory.abi
uniswap/assets/uniswap-v3/pool.abi
uniswap/assets/uniswap-v3/quoter.abi
uniswap/assets/uniswap-v3/router.abi
myb_uniswap_sdk-1.1.0.dist-info/LICENSE
myb_uniswap_sdk-1.1.0.dist-info/METADATA
myb_uniswap_sdk-1.1.0.dist-info/WHEEL
myb_uniswap_sdk-1.1.0.dist-info/top_level.txt
myb_uniswap_sdk-1.1.0.dist-info/RECORD
