Metadata-Version: 2.1
Name: myb-uniswap-sdk
Version: 1.1.0
Summary: Python library for interacting with Uniswap
Home-page: https://github.com/mine-your-business/myb-uniswap-sdk
Author: Mine Your Business
Author-email: mine.your.business.crypto@gmail.com
License: GPL-3
Platform: UNKNOWN
Classifier: Programming Language :: Python :: 3
Classifier: License :: OSI Approved :: GNU General Public License v3 (GPLv3)
Classifier: Operating System :: OS Independent
Requires-Python: >=3.7
License-File: LICENSE
Requires-Dist: requests (>=2.26.0)
Requires-Dist: web3 (>=5.29.0)
Requires-Dist: click (>=8.1.3)
Requires-Dist: python-dotenv (>=0.19.0)
